pssapi/__init__.py
pssapi/client.py
pssapi/client_base.py
pssapi/constants.py
pssapi/core.py
pssapi/exc.py
pssapi/types.py
pssapi/entities/__init__.py
pssapi/entities/achievement_design.py
pssapi/entities/action_type.py
pssapi/entities/add_starbux.py
pssapi/entities/alliance.py
pssapi/entities/animation.py
pssapi/entities/asset.py
pssapi/entities/background.py
pssapi/entities/battle.py
pssapi/entities/challenge_design.py
pssapi/entities/character.py
pssapi/entities/character_action.py
pssapi/entities/character_design.py
pssapi/entities/character_design_action.py
pssapi/entities/character_part.py
pssapi/entities/collection_design.py
pssapi/entities/condition_type.py
pssapi/entities/craft_design.py
pssapi/entities/division_design.py
pssapi/entities/draw_design.py
pssapi/entities/entity_base.py
pssapi/entities/file.py
pssapi/entities/friend.py
pssapi/entities/get_catalog_quantity.py
pssapi/entities/get_current_resources.py
pssapi/entities/history.py
pssapi/entities/item.py
pssapi/entities/item_design.py
pssapi/entities/item_design_action.py
pssapi/entities/league.py
pssapi/entities/list_friends.py
pssapi/entities/live_ops.py
pssapi/entities/message.py
pssapi/entities/missile_design.py
pssapi/entities/mission_design.py
pssapi/entities/mission_event.py
pssapi/entities/news_design.py
pssapi/entities/planet.py
pssapi/entities/prestige.py
pssapi/entities/promotion_design.py
pssapi/entities/research.py
pssapi/entities/research_design.py
pssapi/entities/reward_design.py
pssapi/entities/room.py
pssapi/entities/room_action.py
pssapi/entities/room_design.py
pssapi/entities/room_design_purchase.py
pssapi/entities/room_design_sprite.py
pssapi/entities/sale.py
pssapi/entities/season_design.py
pssapi/entities/setting.py
pssapi/entities/ship.py
pssapi/entities/ship_design.py
pssapi/entities/situation_design.py
pssapi/entities/skin.py
pssapi/entities/skin_set.py
pssapi/entities/sprite.py
pssapi/entities/star_system.py
pssapi/entities/star_system_link.py
pssapi-0.6.0.dist-info/METADATA
pssapi-0.6.0.dist-info/WHEEL
pssapi-0.6.0.dist-info/licenses/LICENSE.md
pssapi-0.6.0.dist-info/RECORD
