Metadata-Version: 2.4
Name: pssapi
Version: 0.6.0
Summary: A wrapper for the Pixel Starships API.
Project-URL: Repository, https://github.com/PSS-Tools-Development/pssapi.py
Project-URL: Issues, https://github.com/PSS-Tools-Development/pssapi.py/issues
Project-URL: Changelog, https://github.com/PSS-Tools-Development/pssapi.py/releases
Author: Solevis, architelos
Author-email: "The worst." <theworstpss@gmail.com>
License-Expression: MIT
License-File: LICENSE.md
Keywords: API,PSS,Pixel Starships
Classifier: Development Status :: 3 - Alpha
Classifier: Framework :: AsyncIO
Classifier: Framework :: Pydantic
Classifier: Framework :: Pydantic :: 2
Classifier: Intended Audience :: Developers
Classifier: License :: OSI Approved :: MIT License
Classifier: Natural Language :: English
Classifier: Operating System :: OS Independent
Classifier: Programming Language :: Python
Classifier: Programming Language :: Python :: 3
Classifier: Programming Language :: Python :: 3 :: Only
Classifier: Programming Language :: Python :: 3.11
Classifier: Programming Language :: Python :: 3.12
Classifier: Topic :: Internet
Classifier: Topic :: Software Development :: Libraries
Classifier: Topic :: Software Development :: Libraries :: Python Modules
Classifier: Topic :: Utilities
Classifier: Typing :: Typed
Requires-Python: >=3.11
Requires-Dist: aiohttp>=3.10.5
Requires-Dist: apscheduler>=3.10.4
Requires-Dist: pytz>=2024.1
Requires-Dist: websockets>=13.0
